{"Id":"moonlitpath_capricious_sky","Guid":"","Name":"Rite of the Capricious Sky","Description":"Numerous versions of this Rite exist, with individual caerns often teaching their members their own localized version. Whether it necessitates solemn chanting, burned offerings, harmonized howling, or complex dances, the result is the same: weather-spirits answer the calls of the Garou. If suitably impressed, the spirits agree to alter local weather patterns to whatever the werewolves wish: clear skies for star gazing, dense fog for getting lost in, lashing rains to deter the wary, and howling winds to erase trails have all seen use by the ever-creative Garou.","System":" A successful test alters the weather patterns within three kilometers of the ritual site for one scene or about an hour. The Difficulty of this Rite depends upon how great the shift in weather patterns is and how rapidly the change needs to occur. Minor changes to weather patterns (increasing or decreasing the temperature by a few degrees, making light clouds clear themselves or produce a light rain) might be Difficulty 2, whereas larger changes (turning those same clouds into a storm or dense fog) are Difficulty 4. Major changes (creating raging storms on an otherwise calm summer day) are Difficulty 6. Such drastic changes both endanger the Veil and anger nature-spirits and are rarely enacted today. Changes occur after a few hours or so but increasing the Difficulty by 1 makes the changes happen within the hour. Each additional point of the Margin can increase the radius of the effect by about three kilometers or increase the duration by about an hour. This Rite cannot produce weather patterns that are utterly impossible for the time or day or season.","Action":[0],"Willpower":"0","Sourcebook_Id":"w5_moonlit_path","DicePool":"Glory + Etiquette","Duration":"","Tags":["weather"],"Version":"1.0.0.4","RageChecks":"0","auspiceRestrictions":[0],"auspiceRenownRequired":-1,"tribeRestrictions":[0],"tribeRenownRequired":-1,"breedRestrictions":[0],"nativeRenownRequired":1,"PrimaryRenown":1,"Ritual":true,"CompatibleForms":[2,3,4]}