{"Id":"w5_break_the_shackles","Guid":"","Name":"Break The Shackles","Description":"A Garou can use this gift to cut through supernatural coercion or outright mind control, severing the chains that bind another person’s mind. Any winged spirit may grant this Gift, as may spirits associated with Gorgon.","System":" The Gift’s user looks into the eyes of the subject and lets out a short, sharp roar, and the player makes a Gift test. The Difficulty depends on the type of effect controlling the subject and the power of the creature behind it, but the default is 3. The Storyteller can allow the subject to add their Resolve to the Gift test pool if they are actively trying to resist the effect themselves.","Action":[2],"Willpower":"0","Sourcebook_Id":"w5_core_rulebook","DicePool":"Resolve + Glory","Duration":"","Tags":["willpower"," healing"," buff"],"Version":"1.0.0.4","RageChecks":"1 Rage Check","auspiceRestrictions":[4],"auspiceRenownRequired":8,"tribeRestrictions":[1],"tribeRenownRequired":9,"breedRestrictions":[0],"nativeRenownRequired":1,"PrimaryRenown":1,"Ritual":false,"CompatibleForms":[2,3,4]}