{"Id":"w5_spiders_song","Guid":"","Name":"Spider's Song","Description":"By listening to the vibrations of the Weaver’s web, the werewolf can eavesdrop on any kind of long-distance verbal communication, whether sent by airborne signal or through a wired connection. The Garou must be aware that a conversation is happening to listen in on it, though they don’t need to know the identities of all the participants. A spider-spirit grants this Gift.","System":"The Garou’s player makes a Resolve + Wisdom test, with the number of successes indicating how much of the conversation they manage to catch. A single success yields only a few scattered words, whereas five or more (or a critical win) allows the user to hear every word, and possibly even identify who’s on the other end of the exchange. For conversations via landlines, the werewolf must place their ear against a telephone wire or cord; to listen in on cell phone discussions, they need only see one of the devices being used. Any encryption increases the Difficulty by 1 or more. This Gift can also be used in homid form.","Action":[2],"Willpower":"1 Willpower","Sourcebook_Id":"w5_core_rulebook","DicePool":"Resolve + Wisdom","Duration":"One Scene","Tags":["surveillance"," stealth"," communication"," ragabash"],"Version":"1.0.0.4","RageChecks":"0","auspiceRestrictions":[1],"auspiceRenownRequired":2,"tribeRestrictions":[6],"tribeRenownRequired":3,"breedRestrictions":[0],"nativeRenownRequired":-1,"PrimaryRenown":3,"Ritual":false,"CompatibleForms":[1,2,3,4]}